scratchai/__init__.py
scratchai/_config.py
scratchai/imgutils.py
scratchai/init.py
scratchai/one_call.py
scratchai/utils.py
scratchai/DataLoader/DataLoader.py
scratchai/DataLoader/DatasetLoader.py
scratchai/DataLoader/ImageLoader.py
scratchai/DataLoader/SegLoader.py
scratchai/DataLoader/__init__.py
scratchai/DataLoader/color_code.py
scratchai/attacks/__init__.py
scratchai/attacks/utils.py
scratchai/attacks/attacks/__init__.py
scratchai/attacks/attacks/deepfool.py
scratchai/attacks/attacks/fast_gradient_method.py
scratchai/attacks/attacks/noise.py
scratchai/attacks/attacks/pgd.py
scratchai/attacks/attacks/saliency_map_method.py
scratchai/attacks/attacks/semantic.py
scratchai/datasets/__init__.py
scratchai/datasets/labels.py
scratchai/learners/__init__.py
scratchai/learners/clflearner.py
scratchai/learners/learner.py
scratchai/learners/metrics.py
scratchai/learners/quicktrain.py
scratchai/nets/__init__.py
scratchai/nets/common.py
scratchai/nets/utils.py
scratchai/nets/blocks/__init__.py
scratchai/nets/blocks/bnconv.py
scratchai/nets/blocks/resblock.py
scratchai/nets/clf/__init__.py
scratchai/nets/clf/alexnet.py
scratchai/nets/clf/googlenet.py
scratchai/nets/clf/lenet.py
scratchai/nets/clf/resnet.py
scratchai/nets/clf/vgg.py
scratchai/nets/gans/__init__.py
scratchai/nets/gans/cycle_gan.py
scratchai/nets/seg/__init__.py
scratchai/nets/seg/enet.py
scratchai/nets/seg/unet.py
scratchai/nets/style_transfer/__init__.py
scratchai/nets/style_transfer/image_transformation_net.py
scratchai/pretrained/__init__.py
scratchai/pretrained/urls.py
tests/__init__.py
tests/test_attacks.py
tests/test_learners.py
tests/test_loaders.py
tests/test_metrics.py
tests/test_nets.py
tests/test_one_calls.py
tests/test_utils.py
scratchai_nightly-0.0.1a3.dist-info/LICENSE
scratchai_nightly-0.0.1a3.dist-info/METADATA
scratchai_nightly-0.0.1a3.dist-info/WHEEL
scratchai_nightly-0.0.1a3.dist-info/top_level.txt
scratchai_nightly-0.0.1a3.dist-info/RECORD
