Metadata-Version: 2.1
Name: scratchai-nightly
Version: 0.0.1a3
Summary: Scratch AI
Home-page: https://github.com/iArunava/scratch.ai
Author: @iArunava
Author-email: iarunavaofficial@gmail.com
License: UNKNOWN
Platform: UNKNOWN
Classifier: Programming Language :: Python :: 3
Classifier: License :: OSI Approved :: MIT License
Classifier: Operating System :: OS Independent
